setup.py
ANT/antdocs.py
ANT/datascripts/__init__.py
ANT/datascripts/datasplit.py
ANT/datascripts/datasplit2.py
ANT/datascripts/datasplitreduced.py
ANT/datascripts/datatest.py
ANT/datascripts/generateTermDoc.py
ANT/datascripts/minsplit.py
ANT/datascripts/mk_data_dir.py
ANT/datascripts/ml100k_item_process.py
ANT/datascripts/ml100k_user_process.py
ANT/datascripts/normalize.py
ANT/datascripts/onehot.py
ANT/datascripts/sparsetxt_to_vec.py
ANT/datascripts/split.py
ANT/datascripts/tfidf_and_binary.py
antk.egg-info/PKG-INFO
antk.egg-info/SOURCES.txt
antk.egg-info/dependency_links.txt
antk.egg-info/not-zip-safe
antk.egg-info/requires.txt
antk.egg-info/top_level.txt