Metadata-Version: 1.1
Name: antk
Version: 0.1
Summary: Automated Neural-graph Toolkit: A Tensorflow wrapper for common deep learning tasks and rapid development of newmodels.
Home-page: http://aarontuor.xyz
Author: Aaron Tuor
Author-email: tuora@students.wwu.edu
License: none
Keywords: Deep Learning,Neural Networks,TensorFlow,Machine Learning,Western Washington University
Platform: UNKNOWN
Classifier: Programming Language :: Python
Classifier: Operating System :: OS Independent
Classifier: Intended Audience :: Science/Research
Classifier: Topic :: Scientific/Engineering
